astexport/__init__.py
astexport/__main__.py
astexport/cli.py
astexport/export.py
astexport/parse.py
astexport/version.py
astexport-1.3.0.dist-info/DESCRIPTION.rst
astexport-1.3.0.dist-info/METADATA
astexport-1.3.0.dist-info/RECORD
astexport-1.3.0.dist-info/WHEEL
astexport-1.3.0.dist-info/entry_points.txt
astexport-1.3.0.dist-info/metadata.json
astexport-1.3.0.dist-info/top_level.txt
