Metadata-Version: 2.0
Name: astexport
Version: 1.3.0
Summary: Python command line application to export Python AST as Json.
Home-page: https://github.com/fpoli/python-astexport
Author: Federico Poli
Author-email: federpoli@gmail.com
License: MIT
Platform: UNKNOWN
Classifier: Development Status :: 4 - Beta
Classifier: Environment :: Console
Classifier: Intended Audience :: Developers
Classifier: Topic :: Software Development :: Compilers
Classifier: Topic :: Software Development :: Disassemblers
Classifier: License :: OSI Approved :: MIT License
Classifier: Operating System :: OS Independent
Classifier: Programming Language :: Python :: 3
Classifier: Programming Language :: Python :: 3.5
Classifier: Programming Language :: Python :: 3.6
Provides-Extra: dev
Requires-Dist: nose (==1.3.3); extra == 'dev'
Requires-Dist: pep8 (==1.4.6); extra == 'dev'
Requires-Dist: twine; extra == 'dev'
